ptbplugins/__init__.py
ptbplugins/jobregistration.py
ptbplugins/pluginregistration.py
ptbplugins/registration.py
ptbplugins-0.0.1.dist-info/DESCRIPTION.rst
ptbplugins-0.0.1.dist-info/METADATA
ptbplugins-0.0.1.dist-info/RECORD
ptbplugins-0.0.1.dist-info/WHEEL
ptbplugins-0.0.1.dist-info/metadata.json
ptbplugins-0.0.1.dist-info/top_level.txt
